setup.py
blogen/__init__.py
blogen/gen.py
blogen.egg-info/PKG-INFO
blogen.egg-info/SOURCES.txt
blogen.egg-info/dependency_links.txt
blogen.egg-info/entry_points.txt
blogen.egg-info/requires.txt
blogen.egg-info/top_level.txt