Metadata-Version: 1.0
Name: blogen
Version: 0.0.0.9.pre
Summary: A local static blog site generator and previewer,that help you deploy blog on github pages
Home-page: https://github.com/ipconfiger/blogen
Author: Alexander.Li
Author-email: superpowerlee@gmail.com
License: LGPL
Keywords: github pages blog
Platform: UNKNOWN
